<?xml version="1.0"?>
<?mso-application progid="Excel.Sheet"?>
<Workbook xmlns="urn:schemas-microsoft-com:office:spreadsheet"
 xmlns:o="urn:schemas-microsoft-com:office:office"
 xmlns:x="urn:schemas-microsoft-com:office:excel"
 xmlns:ss="urn:schemas-microsoft-com:office:spreadsheet"
 xmlns:html="http://www.w3.org/TR/REC-html40">
 <DocumentProperties xmlns="urn:schemas-microsoft-com:office:office">
  <Author>Dube, Michele M</Author>
  <LastAuthor>Pooja Umashankar</LastAuthor>
  <LastPrinted>2020-03-16T08:11:20Z</LastPrinted>
  <Created>2020-01-16T16:45:13Z</Created>
  <LastSaved>2020-03-15T20:36:22Z</LastSaved>
  <Company>UnitedHealth Group</Company>
  <Version>15.00</Version>
 </DocumentProperties>
 <OfficeDocumentSettings xmlns="urn:schemas-microsoft-com:office:office">
  <AllowPNG/>
 </OfficeDocumentSettings>
 <ExcelWorkbook xmlns="urn:schemas-microsoft-com:office:excel">
  <WindowHeight>7310</WindowHeight>
  <WindowWidth>19200</WindowWidth>
  <WindowTopX>0</WindowTopX>
  <WindowTopY>0</WindowTopY>
  <TabRatio>467</TabRatio>
  <ProtectStructure>False</ProtectStructure>
  <ProtectWindows>False</ProtectWindows>
 </ExcelWorkbook>
 <Styles>
  <Style ss:ID="Default" ss:Name="Normal">
   <Alignment ss:Vertical="Bottom"/>
   <Borders/>
   <Font ss:FontName="Calibri" x:Family="Swiss" ss:Size="11" ss:Color="#000000"/>
   <Interior/>
   <NumberFormat/>
   <Protection/>
  </Style>
  <Style ss:ID="m412762832">
   <Alignment ss:Horizontal="Left" ss:Vertical="Top" ss:WrapText="1"/>
   <Borders>
    <Border ss:Position="Bottom" ss:LineStyle="Continuous" ss:Weight="1"/>
    <Border ss:Position="Left" ss:LineStyle="Continuous" ss:Weight="1"/>
    <Border ss:Position="Right" ss:LineStyle="Continuous" ss:Weight="1"/>
    <Border ss:Position="Top" ss:LineStyle="Continuous" ss:Weight="1"/>
   </Borders>
  </Style>
  <Style ss:ID="m412759504">
   <Alignment ss:Horizontal="Left" ss:Vertical="Top" ss:WrapText="1"/>
   <Borders>
    <Border ss:Position="Bottom" ss:LineStyle="Continuous" ss:Weight="1"/>
    <Border ss:Position="Left" ss:LineStyle="Continuous" ss:Weight="1"/>
    <Border ss:Position="Right" ss:LineStyle="Continuous" ss:Weight="1"/>
    <Border ss:Position="Top" ss:LineStyle="Continuous" ss:Weight="1"/>
   </Borders>
  </Style>
  <Style ss:ID="m412759524">
   <Alignment ss:Horizontal="Left" ss:Vertical="Top" ss:WrapText="1"/>
   <Borders>
    <Border ss:Position="Bottom" ss:LineStyle="Continuous" ss:Weight="1"/>
    <Border ss:Position="Left" ss:LineStyle="Continuous" ss:Weight="1"/>
    <Border ss:Position="Right" ss:LineStyle="Continuous" ss:Weight="1"/>
    <Border ss:Position="Top" ss:LineStyle="Continuous" ss:Weight="1"/>
   </Borders>
  </Style>
  <Style ss:ID="m412759544">
   <Alignment ss:Horizontal="Left" ss:Vertical="Top" ss:WrapText="1"/>
   <Borders>
    <Border ss:Position="Bottom" ss:LineStyle="Continuous" ss:Weight="1"/>
    <Border ss:Position="Left" ss:LineStyle="Continuous" ss:Weight="1"/>
    <Border ss:Position="Right" ss:LineStyle="Continuous" ss:Weight="1"/>
    <Border ss:Position="Top" ss:LineStyle="Continuous" ss:Weight="1"/>
   </Borders>
  </Style>
  <Style ss:ID="m412759584">
   <Alignment ss:Horizontal="Left" ss:Vertical="Top" ss:WrapText="1"/>
   <Borders>
    <Border ss:Position="Bottom" ss:LineStyle="Continuous" ss:Weight="1"/>
    <Border ss:Position="Left" ss:LineStyle="Continuous" ss:Weight="1"/>
    <Border ss:Position="Right" ss:LineStyle="Continuous" ss:Weight="1"/>
    <Border ss:Position="Top" ss:LineStyle="Continuous" ss:Weight="1"/>
   </Borders>
  </Style>
  <Style ss:ID="m412759604">
   <Alignment ss:Horizontal="Left" ss:Vertical="Top" ss:WrapText="1"/>
   <Borders>
    <Border ss:Position="Bottom" ss:LineStyle="Continuous" ss:Weight="1"/>
    <Border ss:Position="Left" ss:LineStyle="Continuous" ss:Weight="1"/>
    <Border ss:Position="Right" ss:LineStyle="Continuous" ss:Weight="1"/>
    <Border ss:Position="Top" ss:LineStyle="Continuous" ss:Weight="1"/>
   </Borders>
  </Style>
  <Style ss:ID="m412758880">
   <Alignment ss:Horizontal="Left" ss:Vertical="Top" ss:WrapText="1"/>
   <Borders>
    <Border ss:Position="Bottom" ss:LineStyle="Continuous" ss:Weight="1"/>
    <Border ss:Position="Left" ss:LineStyle="Continuous" ss:Weight="1"/>
    <Border ss:Position="Right" ss:LineStyle="Continuous" ss:Weight="1"/>
    <Border ss:Position="Top" ss:LineStyle="Continuous" ss:Weight="1"/>
   </Borders>
  </Style>
  <Style ss:ID="m412758900">
   <Alignment ss:Horizontal="Left" ss:Vertical="Top" ss:WrapText="1"/>
   <Borders>
    <Border ss:Position="Bottom" ss:LineStyle="Continuous" ss:Weight="1"/>
    <Border ss:Position="Left" ss:LineStyle="Continuous" ss:Weight="1"/>
    <Border ss:Position="Right" ss:LineStyle="Continuous" ss:Weight="1"/>
    <Border ss:Position="Top" ss:LineStyle="Continuous" ss:Weight="1"/>
   </Borders>
  </Style>
  <Style ss:ID="m412758920">
   <Alignment ss:Horizontal="Left" ss:Vertical="Top" ss:WrapText="1"/>
   <Borders>
    <Border ss:Position="Bottom" ss:LineStyle="Continuous" ss:Weight="1"/>
    <Border ss:Position="Left" ss:LineStyle="Continuous" ss:Weight="1"/>
    <Border ss:Position="Right" ss:LineStyle="Continuous" ss:Weight="1"/>
    <Border ss:Position="Top" ss:LineStyle="Continuous" ss:Weight="1"/>
   </Borders>
  </Style>
  <Style ss:ID="m412758960">
   <Alignment ss:Horizontal="Left" ss:Vertical="Top" ss:WrapText="1"/>
   <Borders>
    <Border ss:Position="Bottom" ss:LineStyle="Continuous" ss:Weight="1"/>
    <Border ss:Position="Left" ss:LineStyle="Continuous" ss:Weight="1"/>
    <Border ss:Position="Right" ss:LineStyle="Continuous" ss:Weight="1"/>
    <Border ss:Position="Top" ss:LineStyle="Continuous" ss:Weight="1"/>
   </Borders>
  </Style>
  <Style ss:ID="m412758980">
   <Alignment ss:Horizontal="Left" ss:Vertical="Top" ss:WrapText="1"/>
   <Borders>
    <Border ss:Position="Bottom" ss:LineStyle="Continuous" ss:Weight="1"/>
    <Border ss:Position="Left" ss:LineStyle="Continuous" ss:Weight="1"/>
    <Border ss:Position="Right" ss:LineStyle="Continuous" ss:Weight="1"/>
    <Border ss:Position="Top" ss:LineStyle="Continuous" ss:Weight="1"/>
   </Borders>
  </Style>
  <Style ss:ID="m412763456">
   <Alignment ss:Horizontal="Left" ss:Vertical="Top" ss:WrapText="1"/>
   <Borders>
    <Border ss:Position="Bottom" ss:LineStyle="Continuous" ss:Weight="1"/>
    <Border ss:Position="Left" ss:LineStyle="Continuous" ss:Weight="1"/>
    <Border ss:Position="Right" ss:LineStyle="Continuous" ss:Weight="1"/>
    <Border ss:Position="Top" ss:LineStyle="Continuous" ss:Weight="1"/>
   </Borders>
  </Style>
  <Style ss:ID="m412763476">
   <Alignment ss:Horizontal="Left" ss:Vertical="Top" ss:WrapText="1"/>
   <Borders>
    <Border ss:Position="Bottom" ss:LineStyle="Continuous" ss:Weight="1"/>
    <Border ss:Position="Left" ss:LineStyle="Continuous" ss:Weight="1"/>
    <Border ss:Position="Right" ss:LineStyle="Continuous" ss:Weight="1"/>
    <Border ss:Position="Top" ss:LineStyle="Continuous" ss:Weight="1"/>
   </Borders>
  </Style>
  <Style ss:ID="m412763496">
   <Alignment ss:Horizontal="Left" ss:Vertical="Top" ss:WrapText="1"/>
   <Borders>
    <Border ss:Position="Bottom" ss:LineStyle="Continuous" ss:Weight="1"/>
    <Border ss:Position="Left" ss:LineStyle="Continuous" ss:Weight="1"/>
    <Border ss:Position="Right" ss:LineStyle="Continuous" ss:Weight="1"/>
    <Border ss:Position="Top" ss:LineStyle="Continuous" ss:Weight="1"/>
   </Borders>
  </Style>
  <Style ss:ID="m412763536">
   <Alignment ss:Horizontal="Left" ss:Vertical="Top" ss:WrapText="1"/>
   <Borders>
    <Border ss:Position="Bottom" ss:LineStyle="Continuous" ss:Weight="1"/>
    <Border ss:Position="Left" ss:LineStyle="Continuous" ss:Weight="1"/>
    <Border ss:Position="Right" ss:LineStyle="Continuous" ss:Weight="1"/>
    <Border ss:Position="Top" ss:LineStyle="Continuous" ss:Weight="1"/>
   </Borders>
  </Style>
  <Style ss:ID="m412763556">
   <Alignment ss:Horizontal="Left" ss:Vertical="Top" ss:WrapText="1"/>
   <Borders>
    <Border ss:Position="Bottom" ss:LineStyle="Continuous" ss:Weight="1"/>
    <Border ss:Position="Left" ss:LineStyle="Continuous" ss:Weight="1"/>
    <Border ss:Position="Right" ss:LineStyle="Continuous" ss:Weight="1"/>
    <Border ss:Position="Top" ss:LineStyle="Continuous" ss:Weight="1"/>
   </Borders>
  </Style>
  <Style ss:ID="m412761168">
   <Alignment ss:Horizontal="Left" ss:Vertical="Top" ss:WrapText="1"/>
   <Borders>
    <Border ss:Position="Bottom" ss:LineStyle="Continuous" ss:Weight="1"/>
    <Border ss:Position="Left" ss:LineStyle="Continuous" ss:Weight="1"/>
    <Border ss:Position="Right" ss:LineStyle="Continuous" ss:Weight="1"/>
    <Border ss:Position="Top" ss:LineStyle="Continuous" ss:Weight="1"/>
   </Borders>
  </Style>
  <Style ss:ID="m412761188">
   <Alignment ss:Horizontal="Left" ss:Vertical="Top" ss:WrapText="1"/>
   <Borders>
    <Border ss:Position="Bottom" ss:LineStyle="Continuous" ss:Weight="1"/>
    <Border ss:Position="Left" ss:LineStyle="Continuous" ss:Weight="1"/>
    <Border ss:Position="Right" ss:LineStyle="Continuous" ss:Weight="1"/>
    <Border ss:Position="Top" ss:LineStyle="Continuous" ss:Weight="1"/>
   </Borders>
  </Style>
  <Style ss:ID="m412761208">
   <Alignment ss:Horizontal="Left" ss:Vertical="Top" ss:WrapText="1"/>
   <Borders>
    <Border ss:Position="Bottom" ss:LineStyle="Continuous" ss:Weight="1"/>
    <Border ss:Position="Left" ss:LineStyle="Continuous" ss:Weight="1"/>
    <Border ss:Position="Right" ss:LineStyle="Continuous" ss:Weight="1"/>
    <Border ss:Position="Top" ss:LineStyle="Continuous" ss:Weight="1"/>
   </Borders>
  </Style>
  <Style ss:ID="m412761228">
   <Alignment ss:Horizontal="Left" ss:Vertical="Top" ss:WrapText="1"/>
   <Borders>
    <Border ss:Position="Bottom" ss:LineStyle="Continuous" ss:Weight="1"/>
    <Border ss:Position="Left" ss:LineStyle="Continuous" ss:Weight="1"/>
    <Border ss:Position="Right" ss:LineStyle="Continuous" ss:Weight="1"/>
    <Border ss:Position="Top" ss:LineStyle="Continuous" ss:Weight="1"/>
   </Borders>
  </Style>
  <Style ss:ID="m412761248">
   <Alignment ss:Horizontal="Left" ss:Vertical="Top" ss:WrapText="1"/>
   <Borders>
    <Border ss:Position="Bottom" ss:LineStyle="Continuous" ss:Weight="1"/>
    <Border ss:Position="Left" ss:LineStyle="Continuous" ss:Weight="1"/>
    <Border ss:Position="Right" ss:LineStyle="Continuous" ss:Weight="1"/>
    <Border ss:Position="Top" ss:LineStyle="Continuous" ss:Weight="1"/>
   </Borders>
  </Style>
  <Style ss:ID="m412761268">
   <Alignment ss:Horizontal="Left" ss:Vertical="Top" ss:WrapText="1"/>
   <Borders>
    <Border ss:Position="Bottom" ss:LineStyle="Continuous" ss:Weight="1"/>
    <Border ss:Position="Left" ss:LineStyle="Continuous" ss:Weight="1"/>
    <Border ss:Position="Right" ss:LineStyle="Continuous" ss:Weight="1"/>
    <Border ss:Position="Top" ss:LineStyle="Continuous" ss:Weight="1"/>
   </Borders>
  </Style>
  <Style ss:ID="m412762624">
   <Alignment ss:Horizontal="Left" ss:Vertical="Top" ss:WrapText="1"/>
   <Borders>
    <Border ss:Position="Bottom" ss:LineStyle="Continuous" ss:Weight="1"/>
    <Border ss:Position="Left" ss:LineStyle="Continuous" ss:Weight="1"/>
    <Border ss:Position="Right" ss:LineStyle="Continuous" ss:Weight="1"/>
    <Border ss:Position="Top" ss:LineStyle="Continuous" ss:Weight="1"/>
   </Borders>
  </Style>
  <Style ss:ID="m412762644">
   <Alignment ss:Horizontal="Left" ss:Vertical="Top" ss:WrapText="1"/>
   <Borders>
    <Border ss:Position="Bottom" ss:LineStyle="Continuous" ss:Weight="1"/>
    <Border ss:Position="Left" ss:LineStyle="Continuous" ss:Weight="1"/>
    <Border ss:Position="Right" ss:LineStyle="Continuous" ss:Weight="1"/>
    <Border ss:Position="Top" ss:LineStyle="Continuous" ss:Weight="1"/>
   </Borders>
  </Style>
  <Style ss:ID="m412762664">
   <Alignment ss:Horizontal="Left" ss:Vertical="Top" ss:WrapText="1"/>
   <Borders>
    <Border ss:Position="Bottom" ss:LineStyle="Continuous" ss:Weight="1"/>
    <Border ss:Position="Left" ss:LineStyle="Continuous" ss:Weight="1"/>
    <Border ss:Position="Right" ss:LineStyle="Continuous" ss:Weight="1"/>
    <Border ss:Position="Top" ss:LineStyle="Continuous" ss:Weight="1"/>
   </Borders>
  </Style>
  <Style ss:ID="m412762684">
   <Alignment ss:Horizontal="Left" ss:Vertical="Top" ss:WrapText="1"/>
   <Borders>
    <Border ss:Position="Bottom" ss:LineStyle="Continuous" ss:Weight="1"/>
    <Border ss:Position="Left" ss:LineStyle="Continuous" ss:Weight="1"/>
    <Border ss:Position="Right" ss:LineStyle="Continuous" ss:Weight="1"/>
    <Border ss:Position="Top" ss:LineStyle="Continuous" ss:Weight="1"/>
   </Borders>
  </Style>
  <Style ss:ID="m412762704">
   <Alignment ss:Horizontal="Left" ss:Vertical="Top" ss:WrapText="1"/>
   <Borders>
    <Border ss:Position="Bottom" ss:LineStyle="Continuous" ss:Weight="1"/>
    <Border ss:Position="Left" ss:LineStyle="Continuous" ss:Weight="1"/>
    <Border ss:Position="Right" ss:LineStyle="Continuous" ss:Weight="1"/>
    <Border ss:Position="Top" ss:LineStyle="Continuous" ss:Weight="1"/>
   </Borders>
  </Style>
  <Style ss:ID="m412762000">
   <Alignment ss:Horizontal="Left" ss:Vertical="Top" ss:WrapText="1"/>
   <Borders>
    <Border ss:Position="Bottom" ss:LineStyle="Continuous" ss:Weight="1"/>
    <Border ss:Position="Left" ss:LineStyle="Continuous" ss:Weight="1"/>
    <Border ss:Position="Right" ss:LineStyle="Continuous" ss:Weight="1"/>
    <Border ss:Position="Top" ss:LineStyle="Continuous" ss:Weight="1"/>
   </Borders>
  </Style>
  <Style ss:ID="m412762020">
   <Alignment ss:Horizontal="Left" ss:Vertical="Top" ss:WrapText="1"/>
   <Borders>
    <Border ss:Position="Bottom" ss:LineStyle="Continuous" ss:Weight="1"/>
    <Border ss:Position="Left" ss:LineStyle="Continuous" ss:Weight="1"/>
    <Border ss:Position="Right" ss:LineStyle="Continuous" ss:Weight="1"/>
    <Border ss:Position="Top" ss:LineStyle="Continuous" ss:Weight="1"/>
   </Borders>
  </Style>
  <Style ss:ID="m412762040">
   <Alignment ss:Horizontal="Left" ss:Vertical="Top" ss:WrapText="1"/>
   <Borders>
    <Border ss:Position="Bottom" ss:LineStyle="Continuous" ss:Weight="1"/>
    <Border ss:Position="Left" ss:LineStyle="Continuous" ss:Weight="1"/>
    <Border ss:Position="Right" ss:LineStyle="Continuous" ss:Weight="1"/>
    <Border ss:Position="Top" ss:LineStyle="Continuous" ss:Weight="1"/>
   </Borders>
  </Style>
  <Style ss:ID="m412762060">
   <Alignment ss:Horizontal="Left" ss:Vertical="Top" ss:WrapText="1"/>
   <Borders>
    <Border ss:Position="Bottom" ss:LineStyle="Continuous" ss:Weight="1"/>
    <Border ss:Position="Left" ss:LineStyle="Continuous" ss:Weight="1"/>
    <Border ss:Position="Right" ss:LineStyle="Continuous" ss:Weight="1"/>
    <Border ss:Position="Top" ss:LineStyle="Continuous" ss:Weight="1"/>
   </Borders>
  </Style>
  <Style ss:ID="m412762080">
   <Alignment ss:Horizontal="Left" ss:Vertical="Top" ss:WrapText="1"/>
   <Borders>
    <Border ss:Position="Bottom" ss:LineStyle="Continuous" ss:Weight="1"/>
    <Border ss:Position="Left" ss:LineStyle="Continuous" ss:Weight="1"/>
    <Border ss:Position="Right" ss:LineStyle="Continuous" ss:Weight="1"/>
    <Border ss:Position="Top" ss:LineStyle="Continuous" ss:Weight="1"/>
   </Borders>
  </Style>
  <Style ss:ID="m412762100">
   <Alignment ss:Horizontal="Left" ss:Vertical="Top" ss:WrapText="1"/>
   <Borders>
    <Border ss:Position="Bottom" ss:LineStyle="Continuous" ss:Weight="1"/>
    <Border ss:Position="Left" ss:LineStyle="Continuous" ss:Weight="1"/>
    <Border ss:Position="Right" ss:LineStyle="Continuous" ss:Weight="1"/>
    <Border ss:Position="Top" ss:LineStyle="Continuous" ss:Weight="1"/>
   </Borders>
  </Style>
  <Style ss:ID="m412759296">
   <Alignment ss:Horizontal="Center" ss:Vertical="Center" ss:WrapText="1"/>
   <Borders>
    <Border ss:Position="Bottom" ss:LineStyle="Continuous" ss:Weight="1"/>
    <Border ss:Position="Left" ss:LineStyle="Continuous" ss:Weight="1"/>
    <Border ss:Position="Right" ss:LineStyle="Continuous" ss:Weight="1"/>
    <Border ss:Position="Top" ss:LineStyle="Continuous" ss:Weight="1"/>
   </Borders>
   <Font ss:FontName="Calibri" x:Family="Swiss" ss:Size="12" ss:Color="#003366"
    ss:Bold="1"/>
   <Interior ss:Color="#EDEDED" ss:Pattern="Solid"/>
  </Style>
  <Style ss:ID="m412759316">
   <Alignment ss:Horizontal="Left" ss:Vertical="Top" ss:WrapText="1"/>
   <Borders>
    <Border ss:Position="Bottom" ss:LineStyle="Continuous" ss:Weight="1"/>
    <Border ss:Position="Left" ss:LineStyle="Continuous" ss:Weight="1"/>
    <Border ss:Position="Right" ss:LineStyle="Continuous" ss:Weight="1"/>
    <Border ss:Position="Top" ss:LineStyle="Continuous" ss:Weight="1"/>
   </Borders>
  </Style>
  <Style ss:ID="m412759336">
   <Alignment ss:Horizontal="Left" ss:Vertical="Top" ss:WrapText="1"/>
   <Borders>
    <Border ss:Position="Bottom" ss:LineStyle="Continuous" ss:Weight="1"/>
    <Border ss:Position="Left" ss:LineStyle="Continuous" ss:Weight="1"/>
    <Border ss:Position="Right" ss:LineStyle="Continuous" ss:Weight="1"/>
    <Border ss:Position="Top" ss:LineStyle="Continuous" ss:Weight="1"/>
   </Borders>
  </Style>
  <Style ss:ID="m412759356">
   <Alignment ss:Horizontal="Left" ss:Vertical="Top" ss:WrapText="1"/>
   <Borders>
    <Border ss:Position="Bottom" ss:LineStyle="Continuous" ss:Weight="1"/>
    <Border ss:Position="Left" ss:LineStyle="Continuous" ss:Weight="1"/>
    <Border ss:Position="Right" ss:LineStyle="Continuous" ss:Weight="1"/>
    <Border ss:Position="Top" ss:LineStyle="Continuous" ss:Weight="1"/>
   </Borders>
  </Style>
  <Style ss:ID="m412759376">
   <Alignment ss:Horizontal="Left" ss:Vertical="Top" ss:WrapText="1"/>
   <Borders>
    <Border ss:Position="Bottom" ss:LineStyle="Continuous" ss:Weight="1"/>
    <Border ss:Position="Left" ss:LineStyle="Continuous" ss:Weight="1"/>
    <Border ss:Position="Right" ss:LineStyle="Continuous" ss:Weight="1"/>
    <Border ss:Position="Top" ss:LineStyle="Continuous" ss:Weight="1"/>
   </Borders>
  </Style>
  <Style ss:ID="m412759396">
   <Alignment ss:Horizontal="Left" ss:Vertical="Top" ss:WrapText="1"/>
   <Borders>
    <Border ss:Position="Bottom" ss:LineStyle="Continuous" ss:Weight="1"/>
    <Border ss:Position="Left" ss:LineStyle="Continuous" ss:Weight="1"/>
    <Border ss:Position="Right" ss:LineStyle="Continuous" ss:Weight="1"/>
    <Border ss:Position="Top" ss:LineStyle="Continuous" ss:Weight="1"/>
   </Borders>
  </Style>
  <Style ss:ID="m412759088">
   <Alignment ss:Horizontal="Left" ss:Vertical="Top" ss:WrapText="1"/>
   <Borders>
    <Border ss:Position="Bottom" ss:LineStyle="Continuous" ss:Weight="1"/>
    <Border ss:Position="Left" ss:LineStyle="Continuous" ss:Weight="1"/>
    <Border ss:Position="Right" ss:LineStyle="Continuous" ss:Weight="1"/>
    <Border ss:Position="Top" ss:LineStyle="Continuous" ss:Weight="1"/>
   </Borders>
   <Font ss:FontName="Calibri" x:Family="Swiss" ss:Size="11"/>
  </Style>
  <Style ss:ID="m412759108">
   <Alignment ss:Horizontal="Left" ss:Vertical="Top" ss:WrapText="1"/>
   <Borders>
    <Border ss:Position="Bottom" ss:LineStyle="Continuous" ss:Weight="1"/>
    <Border ss:Position="Left" ss:LineStyle="Continuous" ss:Weight="1"/>
    <Border ss:Position="Right" ss:LineStyle="Continuous" ss:Weight="1"/>
    <Border ss:Position="Top" ss:LineStyle="Continuous" ss:Weight="1"/>
   </Borders>
   <Font ss:FontName="Calibri" x:Family="Swiss" ss:Size="11"/>
  </Style>
  <Style ss:ID="m412759128">
   <Alignment ss:Horizontal="Left" ss:Vertical="Top" ss:WrapText="1"/>
   <Borders>
    <Border ss:Position="Bottom" ss:LineStyle="Continuous" ss:Weight="1"/>
    <Border ss:Position="Left" ss:LineStyle="Continuous" ss:Weight="1"/>
    <Border ss:Position="Right" ss:LineStyle="Continuous" ss:Weight="1"/>
    <Border ss:Position="Top" ss:LineStyle="Continuous" ss:Weight="1"/>
   </Borders>
   <Font ss:FontName="Calibri" x:Family="Swiss" ss:Size="11"/>
  </Style>
  <Style ss:ID="m412759148">
   <Alignment ss:Horizontal="Left" ss:Vertical="Top" ss:WrapText="1"/>
   <Borders>
    <Border ss:Position="Bottom" ss:LineStyle="Continuous" ss:Weight="1"/>
    <Border ss:Position="Left" ss:LineStyle="Continuous" ss:Weight="1"/>
    <Border ss:Position="Right" ss:LineStyle="Continuous" ss:Weight="1"/>
    <Border ss:Position="Top" ss:LineStyle="Continuous" ss:Weight="1"/>
   </Borders>
   <Font ss:FontName="Calibri" x:Family="Swiss" ss:Size="11"/>
  </Style>
  <Style ss:ID="m412759168">
   <Alignment ss:Horizontal="Left" ss:Vertical="Top" ss:WrapText="1"/>
   <Borders>
    <Border ss:Position="Bottom" ss:LineStyle="Continuous" ss:Weight="1"/>
    <Border ss:Position="Left" ss:LineStyle="Continuous" ss:Weight="1"/>
    <Border ss:Position="Right" ss:LineStyle="Continuous" ss:Weight="1"/>
    <Border ss:Position="Top" ss:LineStyle="Continuous" ss:Weight="1"/>
   </Borders>
   <Font ss:FontName="Calibri" x:Family="Swiss" ss:Size="11"/>
  </Style>
  <Style ss:ID="m412759188">
   <Alignment ss:Horizontal="Left" ss:Vertical="Top" ss:WrapText="1"/>
   <Borders>
    <Border ss:Position="Bottom" ss:LineStyle="Continuous" ss:Weight="1"/>
    <Border ss:Position="Left" ss:LineStyle="Continuous" ss:Weight="1"/>
    <Border ss:Position="Right" ss:LineStyle="Continuous" ss:Weight="1"/>
    <Border ss:Position="Top" ss:LineStyle="Continuous" ss:Weight="1"/>
   </Borders>
   <Font ss:FontName="Calibri" x:Family="Swiss" ss:Size="11"/>
  </Style>
  <Style ss:ID="m412761792">
   <Alignment ss:Vertical="Top" ss:WrapText="1"/>
   <Borders>
    <Border ss:Position="Bottom" ss:LineStyle="Continuous" ss:Weight="1"/>
    <Border ss:Position="Left" ss:LineStyle="Continuous" ss:Weight="1"/>
    <Border ss:Position="Right" ss:LineStyle="Continuous" ss:Weight="1"/>
    <Border ss:Position="Top" ss:LineStyle="Continuous" ss:Weight="1"/>
   </Borders>
  </Style>
  <Style ss:ID="m412761812">
   <Alignment ss:Vertical="Top" ss:WrapText="1"/>
   <Borders>
    <Border ss:Position="Bottom" ss:LineStyle="Continuous" ss:Weight="1"/>
    <Border ss:Position="Left" ss:LineStyle="Continuous" ss:Weight="1"/>
    <Border ss:Position="Right" ss:LineStyle="Continuous" ss:Weight="1"/>
    <Border ss:Position="Top" ss:LineStyle="Continuous" ss:Weight="1"/>
   </Borders>
  </Style>
  <Style ss:ID="m412761832">
   <Alignment ss:Vertical="Top" ss:WrapText="1"/>
   <Borders>
    <Border ss:Position="Bottom" ss:LineStyle="Continuous" ss:Weight="1"/>
    <Border ss:Position="Left" ss:LineStyle="Continuous" ss:Weight="1"/>
    <Border ss:Position="Right" ss:LineStyle="Continuous" ss:Weight="1"/>
    <Border ss:Position="Top" ss:LineStyle="Continuous" ss:Weight="1"/>
   </Borders>
  </Style>
  <Style ss:ID="m412761852">
   <Alignment ss:Horizontal="Center" ss:Vertical="Center" ss:WrapText="1"/>
   <Borders>
    <Border ss:Position="Bottom" ss:LineStyle="Continuous" ss:Weight="1"/>
    <Border ss:Position="Left" ss:LineStyle="Continuous" ss:Weight="1"/>
    <Border ss:Position="Right" ss:LineStyle="Continuous" ss:Weight="1"/>
    <Border ss:Position="Top" ss:LineStyle="Continuous" ss:Weight="1"/>
   </Borders>
   <Font ss:FontName="Calibri" x:Family="Swiss" ss:Size="12" ss:Color="#003366"
    ss:Bold="1"/>
   <Interior ss:Color="#EDEDED" ss:Pattern="Solid"/>
  </Style>
  <Style ss:ID="m412761892">
   <Alignment ss:Horizontal="Left" ss:Vertical="Top" ss:WrapText="1"/>
   <Borders>
    <Border ss:Position="Bottom" ss:LineStyle="Continuous" ss:Weight="1"/>
    <Border ss:Position="Left" ss:LineStyle="Continuous" ss:Weight="1"/>
    <Border ss:Position="Right" ss:LineStyle="Continuous" ss:Weight="1"/>
    <Border ss:Position="Top" ss:LineStyle="Continuous" ss:Weight="1"/>
   </Borders>
   <Font ss:FontName="Calibri" x:Family="Swiss" ss:Size="11"/>
  </Style>
  <Style ss:ID="m412760980">
   <Alignment ss:Horizontal="Center" ss:Vertical="Center" ss:WrapText="1"/>
   <Borders>
    <Border ss:Position="Bottom" ss:LineStyle="Continuous" ss:Weight="1"/>
    <Border ss:Position="Left" ss:LineStyle="Continuous" ss:Weight="1"/>
    <Border ss:Position="Right" ss:LineStyle="Continuous" ss:Weight="1"/>
    <Border ss:Position="Top" ss:LineStyle="Continuous" ss:Weight="1"/>
   </Borders>
   <Font ss:FontName="Calibri" x:Family="Swiss" ss:Size="12" ss:Color="#003366"
    ss:Bold="1"/>
   <Interior ss:Color="#EDEDED" ss:Pattern="Solid"/>
  </Style>
  <Style ss:ID="m412761000">
   <Alignment ss:Vertical="Top" ss:WrapText="1"/>
   <Borders>
    <Border ss:Position="Bottom" ss:LineStyle="Continuous" ss:Weight="1"/>
    <Border ss:Position="Left" ss:LineStyle="Continuous" ss:Weight="1"/>
    <Border ss:Position="Right" ss:LineStyle="Continuous" ss:Weight="1"/>
    <Border ss:Position="Top" ss:LineStyle="Continuous" ss:Weight="1"/>
   </Borders>
  </Style>
  <Style ss:ID="m412761020">
   <Alignment ss:Vertical="Top" ss:WrapText="1"/>
   <Borders>
    <Border ss:Position="Bottom" ss:LineStyle="Continuous" ss:Weight="1"/>
    <Border ss:Position="Left" ss:LineStyle="Continuous" ss:Weight="1"/>
    <Border ss:Position="Right" ss:LineStyle="Continuous" ss:Weight="1"/>
    <Border ss:Position="Top" ss:LineStyle="Continuous" ss:Weight="1"/>
   </Borders>
  </Style>
  <Style ss:ID="m412761040">
   <Alignment ss:Vertical="Top" ss:WrapText="1"/>
   <Borders>
    <Border ss:Position="Bottom" ss:LineStyle="Continuous" ss:Weight="1"/>
    <Border ss:Position="Left" ss:LineStyle="Continuous" ss:Weight="1"/>
    <Border ss:Position="Right" ss:LineStyle="Continuous" ss:Weight="1"/>
    <Border ss:Position="Top" ss:LineStyle="Continuous" ss:Weight="1"/>
   </Borders>
  </Style>
  <Style ss:ID="m412761060">
   <Alignment ss:Horizontal="Center" ss:Vertical="Center" ss:WrapText="1"/>
   <Borders>
    <Border ss:Position="Bottom" ss:LineStyle="Continuous" ss:Weight="1"/>
    <Border ss:Position="Left" ss:LineStyle="Continuous" ss:Weight="1"/>
    <Border ss:Position="Right" ss:LineStyle="Continuous" ss:Weight="1"/>
    <Border ss:Position="Top" ss:LineStyle="Continuous" ss:Weight="1"/>
   </Borders>
   <Font ss:FontName="Calibri" x:Family="Swiss" ss:Size="12" ss:Color="#003366"
    ss:Bold="1"/>
   <Interior ss:Color="#EDEDED" ss:Pattern="Solid"/>
  </Style>
  <Style ss:ID="s63">
   <Font ss:FontName="Calibri" x:Family="Swiss" ss:Size="18" ss:Color="#333399"
    ss:Bold="1"/>
  </Style>
  <Style ss:ID="s64">
   <Font ss:FontName="Calibri" x:Family="Swiss" ss:Size="16" ss:Color="#333333"
    ss:Bold="1"/>
   <Interior ss:Color="#9BC2E6" ss:Pattern="Solid"/>
  </Style>
  <Style ss:ID="s65">
   <Font ss:FontName="Calibri" x:Family="Swiss" ss:Size="11" ss:Color="#000000"
    ss:Bold="1"/>
  </Style>
  <Style ss:ID="s66">
   <Alignment ss:Horizontal="Center" ss:Vertical="Center" ss:WrapText="1"/>
   <Borders>
    <Border ss:Position="Bottom" ss:LineStyle="Continuous" ss:Weight="1"/>
    <Border ss:Position="Left" ss:LineStyle="Continuous" ss:Weight="1"/>
    <Border ss:Position="Right" ss:LineStyle="Continuous" ss:Weight="1"/>
    <Border ss:Position="Top" ss:LineStyle="Continuous" ss:Weight="1"/>
   </Borders>
   <Font ss:FontName="Calibri" x:Family="Swiss" ss:Size="12" ss:Color="#003366"
    ss:Bold="1"/>
   <Interior ss:Color="#EDEDED" ss:Pattern="Solid"/>
  </Style>
  <Style ss:ID="s67">
   <Alignment ss:Vertical="Top" ss:WrapText="1"/>
   <Borders>
    <Border ss:Position="Bottom" ss:LineStyle="Continuous" ss:Weight="1"/>
    <Border ss:Position="Left" ss:LineStyle="Continuous" ss:Weight="1"/>
    <Border ss:Position="Right" ss:LineStyle="Continuous" ss:Weight="1"/>
    <Border ss:Position="Top" ss:LineStyle="Continuous" ss:Weight="1"/>
   </Borders>
  </Style>
  <Style ss:ID="s68">
   <Alignment ss:Horizontal="Right" ss:Vertical="Top" ss:WrapText="1"/>
   <Borders>
    <Border ss:Position="Bottom" ss:LineStyle="Continuous" ss:Weight="1"/>
    <Border ss:Position="Left" ss:LineStyle="Continuous" ss:Weight="1"/>
    <Border ss:Position="Right" ss:LineStyle="Continuous" ss:Weight="1"/>
    <Border ss:Position="Top" ss:LineStyle="Continuous" ss:Weight="1"/>
   </Borders>
  </Style>
  <Style ss:ID="s69">
   <Alignment ss:Vertical="Top" ss:WrapText="1"/>
   <Borders>
    <Border ss:Position="Bottom" ss:LineStyle="Continuous" ss:Weight="1"/>
    <Border ss:Position="Left" ss:LineStyle="Continuous" ss:Weight="1"/>
    <Border ss:Position="Right" ss:LineStyle="Continuous" ss:Weight="1"/>
    <Border ss:Position="Top" ss:LineStyle="Continuous" ss:Weight="1"/>
   </Borders>
   <Font ss:FontName="Calibri" x:Family="Swiss" ss:Size="11" ss:Color="#000000"
    ss:Bold="1"/>
  </Style>
  <Style ss:ID="s70">
   <Borders/>
  </Style>
  <Style ss:ID="s71">
   <Borders/>
   <NumberFormat ss:Format="#,##0"/>
  </Style>
  <Style ss:ID="s72">
   <Borders/>
   <NumberFormat ss:Format="0%"/>
  </Style>
  <Style ss:ID="s84">
   <Alignment ss:Horizontal="Center" ss:Vertical="Center" ss:WrapText="1"/>
   <Borders>
    <Border ss:Position="Left" ss:LineStyle="Continuous" ss:Weight="1"/>
    <Border ss:Position="Right" ss:LineStyle="Continuous" ss:Weight="1"/>
    <Border ss:Position="Top" ss:LineStyle="Continuous" ss:Weight="1"/>
	<Border ss:Position="Bottom" ss:LineStyle="Continuous" ss:Weight="1"/>
   </Borders>
   <Font ss:FontName="Calibri" x:Family="Swiss" ss:Size="12" ss:Color="#003366"
    ss:Bold="1"/>
   <Interior ss:Color="#EDEDED" ss:Pattern="Solid"/>
  </Style>
  <Style ss:ID="s85">
   <Alignment ss:Vertical="Top" ss:WrapText="1"/>
   <Borders>
    <Border ss:Position="Bottom" ss:LineStyle="Continuous" ss:Weight="1"/>
    <Border ss:Position="Left" ss:LineStyle="Continuous" ss:Weight="1"/>
    <Border ss:Position="Top" ss:LineStyle="Continuous" ss:Weight="1"/>
   </Borders>
  </Style>
  <Style ss:ID="s87">
   <Alignment ss:Horizontal="Left" ss:Vertical="Top" ss:WrapText="1"/>
   <Borders>
    <Border ss:Position="Bottom" ss:LineStyle="Continuous" ss:Weight="1"/>
    <Border ss:Position="Left" ss:LineStyle="Continuous" ss:Weight="1"/>
    <Border ss:Position="Top" ss:LineStyle="Continuous" ss:Weight="1"/>
   </Borders>
   <Font ss:FontName="Calibri" x:Family="Swiss" ss:Size="11"/>
  </Style>
  <Style ss:ID="s94">
   <Alignment ss:Vertical="Top" ss:WrapText="1"/>
   <Borders>
    <Border ss:Position="Bottom" ss:LineStyle="Continuous" ss:Weight="1"/>
   </Borders>
  </Style>
  <Style ss:ID="s95">
   <Alignment ss:Vertical="Top" ss:WrapText="1"/>
   <Borders>
    <Border ss:Position="Bottom" ss:LineStyle="Continuous" ss:Weight="1"/>
    <Border ss:Position="Top" ss:LineStyle="Continuous" ss:Weight="1"/>
   </Borders>
  </Style>
  <Style ss:ID="s96">
   <Alignment ss:Vertical="Bottom" ss:WrapText="1"/>
   <Borders/>
   <Font ss:FontName="Calibri" x:Family="Swiss" ss:Size="11"/>
  </Style>
  <Style ss:ID="s105">
   <Alignment ss:Horizontal="Left" ss:Vertical="Top" ss:WrapText="1"/>
   <Borders>
    <Border ss:Position="Left" ss:LineStyle="Continuous" ss:Weight="1"/>
   </Borders>
  </Style>
  <Style ss:ID="s92">
   <Alignment ss:Vertical="Top" ss:WrapText="1"/>
   <Borders>
    <Border ss:Position="Bottom" ss:LineStyle="Continuous" ss:Weight="1"/>
    <Border ss:Position="Left" ss:LineStyle="Continuous" ss:Weight="1"/>
    <Border ss:Position="Right" ss:LineStyle="Continuous" ss:Weight="1"/>
    <Border ss:Position="Top" ss:LineStyle="Continuous" ss:Weight="1"/>
   </Borders>
   <Font ss:FontName="Calibri" x:Family="Swiss" ss:Size="11" ss:Color="#000000"
    ss:Bold="1"/>
  </Style>
 </Styles>
 <Worksheet ss:Name="Competitive Landscape">
  <Table>
   <Column ss:AutoFitWidth="0" ss:Width="187"/>
   <Column ss:AutoFitWidth="0" ss:Width="151"/>
   <Column ss:AutoFitWidth="0" ss:Width="141"/>
   <Column ss:AutoFitWidth="0" ss:Width="108.5"/>
   <Column ss:AutoFitWidth="0" ss:Width="201"/>
   <Row ss:AutoFitHeight="0" ss:Height="23.5">
    <Cell ss:MergeAcross="4" ss:StyleID="s63"><Data ss:Type="String">%%Header.companyName@@                                               %%Header.currentDateTime@@</Data></Cell>
   </Row>
   <Row ss:Index="3" ss:AutoFitHeight="0" ss:Height="21">
    <Cell ss:StyleID="s64"><Data ss:Type="String">Pharmacy</Data></Cell>
    <Cell ss:StyleID="s64"/>
    <Cell ss:StyleID="s64"/>
    <Cell ss:StyleID="s64"/>
    <Cell ss:StyleID="s64"/>
   </Row>
   <Row ss:AutoFitHeight="0" ss:Height="26" ss:StyleID="s65">
    <Cell ss:StyleID="s66"><Data ss:Type="String">Pharmacy Carrier</Data></Cell>
    <Cell ss:StyleID="s66"><ss:Data ss:Type="String"
      xmlns="http://www.w3.org/TR/REC-html40"><B><Font html:Color="#003366">Coalition </Font></B><I><Font
        html:Color="#000000">(if applicable)</Font></I></ss:Data></Cell>
    <Cell ss:StyleID="s66"><Data ss:Type="String">Number of Members Held</Data></Cell>
    <Cell ss:StyleID="s66"><Data ss:Type="String">% of Members Held</Data></Cell>
    <Cell ss:StyleID="s66"><Data ss:Type="String">Comments</Data></Cell>
   </Row>
   <Row ss:AutoFitHeight="0" ss:Height="23.5" ss:StyleID="s65">
    <Cell ss:StyleID="##competitorNameStyleId@@"><Data ss:Type="String">%%PharmacyCompetitorRec.CompetitorAccount__r.Name@@</Data></Cell>
    <Cell ss:StyleID="s67"><Data ss:Type="String">%%PharmacyCompetitorRec.Coalition_if_applicable__c@@</Data></Cell>
    <Cell ss:StyleID="s68"><Data ss:Type="String">%%PharmacyCompetitorRec.NumberOfMembersHeld__c@@</Data></Cell>
    <Cell ss:StyleID="s68"><Data ss:Type="String">%%PharmacyCompetitorRec.ofMembersHeld__c@@</Data></Cell>
    <Cell ss:StyleID="s67"><Data ss:Type="String">%%PharmacyCompetitorRec.Comments__c@@</Data></Cell>
   </Row>
   <Row ss:AutoFitHeight="0">
    <Cell ss:StyleID="s70"/>
    <Cell ss:StyleID="s70"/>
    <Cell ss:StyleID="s71"/>
    <Cell ss:StyleID="s72"/>
    <Cell ss:StyleID="s70"/>
   </Row>
   <Row ss:AutoFitHeight="0" ss:Height="21">
    <Cell ss:StyleID="s64"><Data ss:Type="String">Dental</Data></Cell>
    <Cell ss:StyleID="s64"/>
    <Cell ss:StyleID="s64"/>
    <Cell ss:StyleID="s64"/>
    <Cell ss:StyleID="s64"/>
   </Row>
   <Row ss:AutoFitHeight="0" ss:Height="27">
    <Cell ss:StyleID="s66"><Data ss:Type="String">Dental Carrier</Data></Cell>
    <Cell ss:StyleID="s66"><Data ss:Type="String">Number of Members Held</Data></Cell>
    <Cell ss:StyleID="s66"><Data ss:Type="String">% of Members Held</Data></Cell>
    <Cell ss:MergeAcross="1" ss:StyleID="m412760980"><Data ss:Type="String">Comments</Data></Cell>
   </Row>
   <Row ss:AutoFitHeight="0" ss:Height="27">
    <Cell ss:StyleID="##competitorNameStyleId@@"><Data ss:Type="String">%%DentalCompetitorRec.CompetitorAccount__r.Name@@</Data></Cell>
    <Cell ss:StyleID="s68"><Data ss:Type="String">%%DentalCompetitorRec.NumberOfMembersHeld__c@@</Data></Cell>
    <Cell ss:StyleID="s68"><Data ss:Type="String">%%DentalCompetitorRec.ofMembersHeld__c@@</Data></Cell>
    <Cell ss:MergeAcross="1" ss:StyleID="m412761000"><Data ss:Type="String">%%DentalCompetitorRec.Comments__c@@</Data></Cell>
   </Row>
   <Row ss:AutoFitHeight="0">
    <Cell ss:StyleID="s70"/>
    <Cell ss:StyleID="s71"/>
    <Cell ss:StyleID="s72"/>
    <Cell ss:StyleID="s70"/>
    <Cell ss:StyleID="s70"/>
   </Row>
   <Row ss:AutoFitHeight="0" ss:Height="21">
    <Cell ss:StyleID="s64"><Data ss:Type="String">Vision</Data></Cell>
    <Cell ss:StyleID="s64"/>
    <Cell ss:StyleID="s64"/>
    <Cell ss:StyleID="s64"/>
    <Cell ss:StyleID="s64"/>
   </Row>
   <Row ss:AutoFitHeight="0" ss:Height="26.5">
    <Cell ss:StyleID="s66"><Data ss:Type="String">Vision Carrier</Data></Cell>
    <Cell ss:StyleID="s66"><Data ss:Type="String">Number of Members Held</Data></Cell>
    <Cell ss:StyleID="s66"><Data ss:Type="String">% of Members Held</Data></Cell>
    <Cell ss:MergeAcross="1" ss:StyleID="m412761060"><Data ss:Type="String">Comments</Data></Cell>
   </Row>
   <Row ss:AutoFitHeight="0" ss:Height="26.5">
    <Cell ss:StyleID="##competitorNameStyleId@@"><Data ss:Type="String">%%VisionCompetitorRec.CompetitorAccount__r.Name@@</Data></Cell>
    <Cell ss:StyleID="s68"><Data ss:Type="String">%%VisionCompetitorRec.NumberOfMembersHeld__c@@</Data></Cell>
    <Cell ss:StyleID="s68"><Data ss:Type="String">%%VisionCompetitorRec.ofMembersHeld__c@@</Data></Cell>
    <Cell ss:MergeAcross="1" ss:StyleID="m412761792"><Data ss:Type="String">%%VisionCompetitorRec.Comments__c@@</Data></Cell>
   </Row>
   <Row ss:AutoFitHeight="0">
    <Cell ss:StyleID="s70"/>
    <Cell ss:StyleID="s71"/>
    <Cell ss:StyleID="s72"/>
    <Cell ss:StyleID="s70"/>
    <Cell ss:StyleID="s70"/>
   </Row>
   <Row ss:AutoFitHeight="0">
    <Cell ss:StyleID="s70"/>
    <Cell ss:StyleID="s96"/>
    <Cell ss:StyleID="s70"/>
    <Cell ss:StyleID="s70"/>
   </Row>
   <Row ss:AutoFitHeight="0" ss:Height="21">
    <Cell ss:StyleID="s64"><Data ss:Type="String">Other Products\Services</Data></Cell>
    <Cell ss:StyleID="s64"/>
    <Cell ss:StyleID="s64"/>
    <Cell ss:StyleID="s64"/>
	<Cell ss:StyleID="s64"/>
	<Cell ss:StyleID="s64"/>
	<Cell ss:StyleID="s64"/>
	<Cell ss:StyleID="s64"/>
	<Cell ss:StyleID="s64"/>
	<Cell ss:StyleID="s64"/>
	<Cell ss:StyleID="s64"/>
	<Cell ss:StyleID="s64"/>
	<Cell ss:StyleID="s64"/>
	<Cell ss:StyleID="s64"/>
    <Cell ss:StyleID="s65"/>
   </Row>
   <Row ss:AutoFitHeight="0" ss:Height="36" ss:StyleID="s65">
    <Cell ss:StyleID="s66"><Data ss:Type="String">Other Products\Services Carrier</Data></Cell>
    <Cell ss:StyleID="m412759296"><Data ss:Type="String">Type of Other Products\Services Provided</Data></Cell>
    <Cell ss:StyleID="s66"><Data ss:Type="String">Contract Type</Data></Cell>
    <Cell ss:MergeAcross="1" ss:StyleID="m412759296"><Data ss:Type="String">Set Up/Data Exchanges</Data></Cell>
    <Cell ss:MergeAcross="2" ss:StyleID="s66"><Data ss:Type="String">Special MyUhc.com Customization</Data></Cell>
    <Cell ss:MergeAcross="5" ss:StyleID="m412759296"><Data ss:Type="String">Notes</Data></Cell>
   </Row>
   <Row ss:AutoFitHeight="0" ss:Height="45">
    <Cell ss:StyleID="##competitorNameStyleId@@"><Data ss:Type="String">%%OtherCompetitorRecByProductOrService.CompetitorAccount__r.Name@@</Data></Cell>
    <Cell ss:StyleID="m412759316"><Data ss:Type="String">%%OtherCompetitorRecByProductOrService.Type_of_Products_Services_Provided__c@@</Data></Cell>
    <Cell ss:StyleID="m412759316"><Data ss:Type="String">%%OtherCompetitorRecByProductOrService.Hub_vendor__c@@</Data></Cell>
    <Cell ss:MergeAcross="1" ss:StyleID="m412759316"><Data ss:Type="String">%%OtherCompetitorRecByProductOrService.Type_of_File__c@@</Data></Cell>
    <Cell ss:MergeAcross="2" ss:StyleID="m412759316"><Data ss:Type="String">%%OtherCompetitorRecByProductOrService.Special_MyUhc_com_Customization_column__c@@</Data></Cell>
    <Cell ss:MergeAcross="5" ss:StyleID="m412759316"><Data ss:Type="String">%%OtherCompetitorRecByProductOrService.Comments__c@@</Data></Cell>
   </Row>
  </Table>
  <WorksheetOptions xmlns="urn:schemas-microsoft-com:office:excel">
   <PageSetup>
    <Header x:Margin="0.3"/>
    <Footer x:Margin="0.3"/>
    <PageMargins x:Bottom="0.75" x:Left="0.25" x:Right="0.25" x:Top="0.75"/>
   </PageSetup>
   <Unsynced/>
   <Print>
    <ValidPrinterInfo/>
    <Scale>71</Scale>
    <HorizontalResolution>600</HorizontalResolution>
    <VerticalResolution>600</VerticalResolution>
   </Print>
   <PageBreakZoom>60</PageBreakZoom>
   <Selected/>
   <Panes>
    <Pane>
     <Number>3</Number>
     <ActiveRow>4</ActiveRow>
    </Pane>
   </Panes>
   <ProtectObjects>False</ProtectObjects>
   <ProtectScenarios>False</ProtectScenarios>
  </WorksheetOptions>
  <PageBreaks xmlns="urn:schemas-microsoft-com:office:excel">
   <RowBreaks>
    <RowBreak>
     <Row>##othrPrdctsViewByCarrierPgBrkRowNo@@</Row>
    </RowBreak>
    <RowBreak>
     <Row>##othrPrdctsViewByPrdctPgBrkRowNo@@</Row>
    </RowBreak>
   </RowBreaks>
  </PageBreaks>
 </Worksheet>
</Workbook>
